plummer/__init__.py
plummer-0.1.2.dist-info/LICENSE
plummer-0.1.2.dist-info/METADATA
plummer-0.1.2.dist-info/WHEEL
plummer-0.1.2.dist-info/top_level.txt
plummer-0.1.2.dist-info/RECORD
