Metadata-Version: 2.1
Name: plummer
Version: 0.1.2
Summary: This is a wrapper around the Plumbum python package.
Author-email: Tyler Petrov <tylerpetrov16@gmail.com>
Project-URL: Homepage, https://github.com/Tyler-Petrov/plummer
Project-URL: Issues, https://github.com/Tyler-Petrov/plummer/issues
Classifier: Programming Language :: Python :: 3
Classifier: License :: OSI Approved :: MIT License
Classifier: Operating System :: OS Independent
Requires-Python: >=3.6
License-File: LICENSE
